asciicast2movie.py
asciicast2movie-0.3.5.dist-info/LICENSE
asciicast2movie-0.3.5.dist-info/METADATA
asciicast2movie-0.3.5.dist-info/WHEEL
asciicast2movie-0.3.5.dist-info/entry_points.txt
asciicast2movie-0.3.5.dist-info/top_level.txt
asciicast2movie-0.3.5.dist-info/RECORD
