Metadata-Version: 2.1
Name: asciicast2movie
Version: 0.3.5
Summary: generate movie (video clip) from asciicast
Home-page: https://bitbucket.org/OpCode-eu-org/asciicast2movie/
Author: Robert Paciorek
Author-email: robert@opcode.eu.org
License: MIT
Project-URL: GitHub, https://github.com/opcode-eu-org-libs/asciicast2movie/
Keywords: asciicast video movie mp4 tty pyte moviepy
Platform: UNKNOWN
Classifier: Programming Language :: Python :: 3
Classifier: License :: OSI Approved :: MIT License
Classifier: Operating System :: OS Independent
Requires-Python: >=3.5
Requires-Dist: moviepy
Requires-Dist: tty2img
